bpsrender/__init__.py
bpsrender/__main__.py
bpsrender/calls.py
bpsrender/commands.py
bpsrender/config.py
bpsrender/helpers.py
bpsrender/setup.py
bpsrender/bscripts/mixdown.py
bpsrender/bscripts/probe.py
bpsrender/bscripts/video.py
bpsrender-0.1.40.post2.dist-info/METADATA
bpsrender-0.1.40.post2.dist-info/RECORD
bpsrender-0.1.40.post2.dist-info/WHEEL
bpsrender-0.1.40.post2.dist-info/entry_points.txt
bpsrender-0.1.40.post2.dist-info/top_level.txt
