Metadata-Version: 2.1
Name: bpsrender
Version: 0.1.40.post2
Summary: Blender Power Sequencer Renderer
Home-page: https://github.com/gdquest/BPSRender
Author: Răzvan C. Rădulescu
Author-email: razcore.art@gmail.com
License: GPLv3
Keywords: blender render parallel multiprocess speedup utility productivty
Platform: UNKNOWN
Classifier: Development Status :: 4 - Beta
Classifier: Environment :: Console
Classifier: Intended Audience :: End Users/Desktop
Classifier: License :: OSI Approved :: GNU General Public License v3 (GPLv3)
Classifier: Natural Language :: English
Classifier: Programming Language :: Python :: 3.3
Classifier: Programming Language :: Python :: 3.4
Classifier: Programming Language :: Python :: 3.5
Classifier: Programming Language :: Python :: 3.6
Classifier: Programming Language :: Python :: 3.7
Classifier: Topic :: Text Processing :: Linguistic
Classifier: Topic :: Multimedia :: Video
Classifier: Topic :: Utilities
Requires-Dist: tqdm
